yorkpy/__init__.py
yorkpy/analytics.py
yorkpy-0.0.11.dist-info/LICENSE.txt
yorkpy-0.0.11.dist-info/METADATA
yorkpy-0.0.11.dist-info/WHEEL
yorkpy-0.0.11.dist-info/top_level.txt
yorkpy-0.0.11.dist-info/RECORD
