Metadata-Version: 2.1
Name: yorkpy
Version: 0.0.11
Summary: Analyze T20 matches based on data from Cricsheet-http://cricsheet.org
Home-page: https://github.com/tvganesh/yorkpy
Author: Tinniam V Ganesh
Author-email: tvganesh.85@gmail.com
License: UNKNOWN
Platform: UNKNOWN
Classifier: Programming Language :: Python :: 3
Classifier: License :: OSI Approved :: MIT License
Classifier: Operating System :: OS Independent
